{
"AOEFRGS": "emotion",
"KAFRL": "camel",
"KPWAEUR": "impair",
"KPWEFRT": "imperative",
"KPWHREPLT": "implement",
"KPWOBL": "impossible",
"KPWORPBT": "important",
"KPWORT": "import",
"KPWOURBGT": "encounter",
"KPWR*EGS": "impression",
"KPWRES": "impress",
"KPWROF": "improve",
"KPWROFPLT": "improvement",
"KPWUT": "input",
"SKP*EPT": "accept",
"SKPA*PL": "example",
"SKPABGT": "exact",
"SKPABLGT": "exactly",
"SKPAOED": "exceed",
"SKPAOERPBS": "experience",
"SKPAOEUR": "expire",
"SKPAOEUT": "excite",
"SKPAOUD": "exude",
"SKPAOUS": "excuse",
"SKPAPBD": "expand",
"SKPAPBGS": "expansion",
"SKPAPL": "exam",
"SKPAUFT": ".",
"SKPEBGT": "expect",
"SKPEFPBS": "expensive",
"SKPEL": "expel",
"SKPEPBD": "extend",
"SKPEPBGS": "extension",
"SKPEPBS": "expense",
"SKPEPT": "except",
"SKPERPBL": "external",
"SKPERPT": "expert",
"SKPES": "access",
"SKPEUFPBS": "existence",
"SKPEUFS": "existence",
"SKPEUFT": "exist",
"SKPEUT": "exit",
"SKPHRAEUPB": "explain",
"SKPHRAOUD": "exclude",
"SKPHREPBT": "excellent",
"SKPHRERPBL": "externally",
"SKPHREUFLT": "explicitly",
"SKPHREUFT": "explicit",
"SKPHROEGS": "explosion",
"SKPORT": "export",
"SKPRA": "extra",
"SKPRABGT": "extract",
"SKPRAEUGS": "expiration",
"SKPREGS": "expression",
"SKPRERPBL": "external",
"SKPRORD": "extraordinary"
}